sphinx_yaml_table/__init__.py
sphinx_yaml_table-0.1.1.dist-info/LICENSE
sphinx_yaml_table-0.1.1.dist-info/WHEEL
sphinx_yaml_table-0.1.1.dist-info/METADATA
sphinx_yaml_table-0.1.1.dist-info/RECORD
