Metadata-Version: 2.1
Name: sphinx-yaml-table
Version: 0.1.1
Summary: yaml-table directive for Sphinx/docutils
Author: Richard Darst
Requires-Python: >=3
Classifier: Programming Language :: Python :: 3
Classifier: License :: OSI Approved :: MIT License
Classifier: Framework :: Sphinx
Classifier: Framework :: Sphinx :: Extension
Requires-Dist: docutils
Requires-Dist: PyYAML
Requires-Dist: sphinx>1.8 ; extra == "test"
Requires-Dist: pytest ; extra == "test"
Project-URL: Home, https://github.com/rkdarst/sphinx-yaml-table/
Provides-Extra: test
